email_utils/__init__.py
email_utils/tests/__init__.py
email_utils/tests/test_send_email.py
django_email_utils-1.0.0.dist-info/LICENSE
django_email_utils-1.0.0.dist-info/METADATA
django_email_utils-1.0.0.dist-info/WHEEL
django_email_utils-1.0.0.dist-info/top_level.txt
django_email_utils-1.0.0.dist-info/RECORD
